pyweb3/__init__.py
pyweb3/http_client.py
pyweb3/json_rpc.py
pyweb3/tls_socket.py
pyweb3/web3client.py
pyweb3/websocket.py
pyweb3-0.1.7.dist-info/LICENSE
pyweb3-0.1.7.dist-info/METADATA
pyweb3-0.1.7.dist-info/WHEEL
pyweb3-0.1.7.dist-info/top_level.txt
pyweb3-0.1.7.dist-info/RECORD
