Metadata-Version: 2.1
Name: pyweb3
Version: 0.1.7
Summary: Web3 RPC client for Python wallets
Home-page: https://github.com/bitlogik/pyWeb3
Author: BitLogiK
Author-email: contact@bitlogik.fr
License: GPLv3
Keywords: web3 blockchain wallet cryptography
Platform: UNKNOWN
Classifier: Programming Language :: Python :: 3 :: Only
Classifier: License :: OSI Approved :: GNU General Public License v3 (GPLv3)
Classifier: Development Status :: 5 - Production/Stable
Classifier: Intended Audience :: Developers
Classifier: Intended Audience :: Information Technology
Classifier: Intended Audience :: System Administrators
Classifier: Intended Audience :: Telecommunications Industry
Classifier: Topic :: Security :: Cryptography
Classifier: Topic :: Software Development :: Libraries :: Python Modules
Requires-Python: >=3.6.1
Requires-Dist: wsproto (>=1.0.0)
Requires-Dist: h11 (<1,>=0.9.0)
